tldr/__init__.py
tldr/cli.py
tldr/config.py
tldr/parser.py
tldr.py-0.8.0.dist-info/LICENSE
tldr.py-0.8.0.dist-info/METADATA
tldr.py-0.8.0.dist-info/WHEEL
tldr.py-0.8.0.dist-info/entry_points.txt
tldr.py-0.8.0.dist-info/top_level.txt
tldr.py-0.8.0.dist-info/RECORD
