Metadata-Version: 2.1
Name: tldr.py
Version: 0.8.0
Summary: A python client for tldr: simplified and community-driven man pages.
Home-page: https://github.com/lord63/tldr.py
Author: lord63
Author-email: lord63.j@gmail.com
License: MIT
Keywords: tldr cli man command usage
Platform: UNKNOWN
Classifier: Development Status :: 4 - Beta
Classifier: Operating System :: POSIX
Classifier: Operating System :: POSIX :: Linux
Classifier: License :: OSI Approved :: MIT License
Classifier: Programming Language :: Python :: 2
Classifier: Programming Language :: Python :: 2.7
Classifier: Programming Language :: Python :: 3
Classifier: Programming Language :: Python :: 3.5
Classifier: Programming Language :: Python :: 3.6
Classifier: Programming Language :: Python :: 3.7
Classifier: Programming Language :: Python :: 3.8
Requires-Dist: click (>=5.0)
Requires-Dist: PyYAML (>=3.11)
